MANIFEST.in
README.rst
bootstrap-buildout.py
buildout.cfg
requirements.txt
setup.py
version.txt
bob/__init__.py
bob.db.verification.utils.egg-info/PKG-INFO
bob.db.verification.utils.egg-info/SOURCES.txt
bob.db.verification.utils.egg-info/dependency_links.txt
bob.db.verification.utils.egg-info/requires.txt
bob.db.verification.utils.egg-info/top_level.txt
bob/db/__init__.py
bob/db/verification/__init__.py
bob/db/verification/utils/__init__.py
bob/db/verification/utils/annotations.py
bob/db/verification/utils/database.py
bob/db/verification/utils/file.py
bob/db/verification/utils/test.py
bob/db/verification/utils/data/eyecenter.pos
bob/db/verification/utils/data/idiap.pos
bob/db/verification/utils/data/named.pos
bob/db/verification/utils/data/test_db.sql3
doc/conf.py
doc/extend.rst
doc/guide.rst
doc/implemented.rst
doc/index.rst
doc/py_api.rst