Metadata-Version: 1.1
Name: bob.db.verification.utils
Version: 2.0.6
Summary: Utilities for bob.db verification databases
Home-page: http://github.com/bioidiap/bob.db.verification.utils
Author: Manuel Guenther
Author-email: manuel.guenther@idiap.ch
License: GPLv3
Keywords: bob,bob.db,verification,utilities
Platform: UNKNOWN
Classifier: Framework :: Bob
Classifier: Development Status :: 4 - Beta
Classifier: Intended Audience :: Developers
Classifier: License :: OSI Approved :: GNU General Public License v3 (GPLv3)
Classifier: Natural Language :: English
Classifier: Programming Language :: Python
Classifier: Programming Language :: Python :: 3
Classifier: Topic :: Scientific/Engineering :: Artificial Intelligence
